powa/__init__.py
powa/collector.py
powa/compat.py
powa/config.py
powa/dashboards.py
powa/database.py
powa/framework.py
powa/function.py
powa/io.py
powa/io_template.py
powa/json.py
powa/options.py
powa/overview.py
powa/powa.wsgi
powa/qual.py
powa/query.py
powa/server.py
powa/slru.py
powa/ui_methods.py
powa/ui_modules.py
powa/user.py
powa/wizard.py
powa/sql/__init__.py
powa/sql/compat.py
powa/sql/tables.py
powa/sql/utils.py
powa/sql/views.py
powa/sql/views_graph.py
powa/sql/views_grid.py
powa/static/css/foundation-icons.eot
powa/static/css/foundation-icons.svg
powa/static/css/foundation-icons.ttf
powa/static/css/foundation-icons.woff
powa/static/css/powa-all.min.css
powa/static/css/powa-all.min.css.map
powa/static/css/translucent.css
powa/static/dist/.vite/manifest.json
powa/static/dist/assets/d3-C1z745ZZ.js
powa/static/dist/assets/d3-GY-Jf1db.js
powa/static/dist/assets/highlight-CRyVn9mj.js
powa/static/dist/assets/highlight-YK6wctMS.js
powa/static/dist/assets/lodash-BwctMegf.js
powa/static/dist/assets/lodash-CmFMvF3r.js
powa/static/dist/assets/luxon-DQMALRfl.js
powa/static/dist/assets/luxon-lqzArHOP.js
powa/static/dist/assets/main-BQBMx7EO.js
powa/static/dist/assets/main-BgNP5mCD.js
powa/static/dist/assets/main-D-n2EdIa.css
powa/static/dist/assets/main-DINs4ZEY.js
powa/static/dist/assets/main-OiFLL3TG.css
powa/static/dist/assets/moment-C5S46NFB.js
powa/static/dist/assets/sqltools-formatter-DsERe3kC.js
powa/static/dist/assets/sqltools-formatter-M1RRnKbr.js
powa/static/dist/assets/vue-CwxuVOXE.js
powa/static/dist/assets/vue-SrZHs5Ax.js
powa/static/dist/assets/vuetify-Bf0BnRvR.js
powa/static/dist/assets/vuetify-K_Anlx4M.js
powa/static/img/powa-logo-white.png
powa/static/img/favicon/apple-touch-icon-114x114.png
powa/static/img/favicon/apple-touch-icon-120x120.png
powa/static/img/favicon/apple-touch-icon-144x144.png
powa/static/img/favicon/apple-touch-icon-152x152.png
powa/static/img/favicon/apple-touch-icon-57x57.png
powa/static/img/favicon/apple-touch-icon-60x60.png
powa_web-5.1.2.dist-info/METADATA
powa_web-5.1.2.dist-info/WHEEL
powa_web-5.1.2.dist-info/top_level.txt
powa_web-5.1.2.dist-info/RECORD
