Metadata-Version: 2.4
Name: powa-web
Version: 5.1.2
Summary: A User Interface for the PoWA project
Home-page: https://powa.readthedocs.io/
Author: powa-team
License: Postgresql
Classifier: Development Status :: 5 - Production/Stable
Classifier: Intended Audience :: System Administrators
Classifier: Intended Audience :: End Users/Desktop
Classifier: License :: Other/Proprietary License
Classifier: License :: OSI Approved :: BSD License
Classifier: Operating System :: OS Independent
Classifier: Programming Language :: Python :: 2
Classifier: Programming Language :: Python :: 3
Classifier: Topic :: Database :: Front-Ends
Requires-Dist: tornado>=2.0
Requires-Dist: psycopg2
Dynamic: author
Dynamic: classifier
Dynamic: description
Dynamic: home-page
Dynamic: license
Dynamic: requires-dist
Dynamic: summary
